marchalib/__init__.py
marchalib/benjamin_danly.py
marchalib/cart2hp.py
marchalib/constant.py
marchalib/edges.py
marchalib/fBms.py
marchalib/fluid.py
marchalib/gauss_beam.py
marchalib/plot.py
marchalib/powerspectrum.py
marchalib/powspec.py
marchalib/projection.py
marchalib/setup_plot.py
marchalib/structuref.py
marchalib/variance.py
marchalib/variance_vz.py
marchalib/vdev.py
marchalib/velocity.py
marchalib/wolfire.py
marchalib-0.1.8.dist-info/LICENSE
marchalib-0.1.8.dist-info/METADATA
marchalib-0.1.8.dist-info/WHEEL
marchalib-0.1.8.dist-info/top_level.txt
marchalib-0.1.8.dist-info/RECORD
