Metadata-Version: 2.1
Name: marchalib
Version: 0.1.8
Summary: A. Marchal library
Home-page: UNKNOWN
Author: Antoine Marchal
Author-email: amarchal@cita.utoronto.ca
License: THE WORK (AS DEFINED BELOW) IS PROVIDED UNDER THE TERMS OF THIS CREATIVE COMMONS PUBLIC LICENSE ("CCPL" OR "LICENSE"). THE WORK IS PROTECTED BY COPYRIGHT AND/OR OTHER APPLICABLE LAW. ANY USE OF THE WORK OTHER THAN AS AUTHORIZED UNDER THIS LICENSE OR COPYRIGHT LAW IS PROHIBITED.
Requires-Dist: numpy
Requires-Dist: statsmodels
Requires-Dist: scipy
Requires-Dist: astropy
Requires-Dist: colorcet
Requires-Dist: healpy
Requires-Dist: galpy
Requires-Dist: pynverse
